zzhprobsixth/Binomialdistribution.py
zzhprobsixth/Gaussiandistribution.py
zzhprobsixth/Generaldistribution.py
zzhprobsixth/__init__.py
zzhprobsixth-0.3.dist-info/METADATA
zzhprobsixth-0.3.dist-info/WHEEL
zzhprobsixth-0.3.dist-info/top_level.txt
zzhprobsixth-0.3.dist-info/RECORD
